[{"date": "23-April-2023", "pages": "Thank you it wasgreate"}, {"date": "23-April-2023", "pages": "fghfsghs"}, {"date": "23-April-2023", "pages": "fhfghgfh"}, {"date": "23-April-2023", "pages": "dttdhdt"}, {"date": "27-April-2023", "pages": "Thank you good"}, {"date": "27-April-2023", "pages": "Not bad"}, {"date": "27-April-2023", "pages": "not bad"}, {"date": "27-April-2023", "pages": "nokjkd"}, {"date": "27-April-2023", "pages": "oirrjg"}, {"date": "27-April-2023", "pages": "rijtjf"}, {"date": "27-April-2023", "pages": "kjgfkjk"}, {"date": "27-April-2023", "pages": "dgjdfn"}, {"date": "27-April-2023", "pages": "zjirstjz"}, {"date": "27-April-2023", "pages": "dghdjfh"}, {"date": "27-April-2023", "pages": "fjgfkn"}, {"date": "27-April-2023", "pages": "rktokz"}, {"date": "27-April-2023", "pages": "\u00f6jfgh"}, {"date": "27-April-2023", "pages": "orijrtjh"}, {"date": "27-April-2023", "pages": "fjgkfjg"}, {"date": "27-April-2023", "pages": "jzkhgfjkhl"}, {"date": "27-April-2023", "pages": "rijgdfj"}, {"date": "27-April-2023", "pages": "iozjifj"}, {"date": "27-April-2023", "pages": "tizkotgkh"}, {"date": "27-April-2023", "pages": "fgjkfd"}, {"date": "27-April-2023", "pages": "jdgdjfn"}, {"date": "27-April-2023", "pages": "kgjklfdjgkl"}, {"date": "27-April-2023", "pages": "jkfjglk\u00f6f"}, {"date": "27-April-2023", "pages": "jgl\u00f6kfdjh"}, {"date": "27-April-2023", "pages": "fgjdfkjf"}, {"date": "27-April-2023", "pages": "shjkgfj\u00f6"}, {"date": "27-April-2023", "pages": "fkjglkf\u00f6jg"}, {"date": "27-April-2023", "pages": "kdlfjg"}, {"date": "27-April-2023", "pages": "hkjl\u00f6c"}, {"date": "05-May-2023", "pages": "Thank you good"}]